README.md
setup.py
exmoset/__init__.py
exmoset/molspace.py
exmoset.egg-info/PKG-INFO
exmoset.egg-info/SOURCES.txt
exmoset.egg-info/dependency_links.txt
exmoset.egg-info/requires.txt
exmoset.egg-info/top_level.txt
exmoset/data/__init__.py
exmoset/data/molecules.py
exmoset/fingerprints/__init__.py
exmoset/fingerprints/containsatom.py
exmoset/fingerprints/containsbond.py
exmoset/fingerprints/fingerprint.py
exmoset/fingerprints/general.py
exmoset/fingerprints/substructure.py
exmoset/fingerprints/template_fingerprint.py
exmoset/molecule/__init__.py
exmoset/molecule/molecule.py
exmoset/plotting/__init__.py
exmoset/plotting/plot_embedded.py
tests/__init__.py
tests/fingerprints.py
tests/tests.py