Metadata-Version: 2.1
Name: exmoset
Version: 0.1.0
Summary: Automating the generation of human readable descriptions of arbitrary subsets of molecular space.
Home-page: https://github.com/acmater/exmoset
Author: Adam Mater
Author-email: adam.mater@anu.edu.au
License: UNKNOWN
Project-URL: Source, https://github.com/acmater/exmoset
Keywords: cheminformatics,clustering,explainable-ml
Platform: UNKNOWN
Classifier: Development Status :: 3 - Alpha
Classifier: Intended Audience :: Science/Research
Classifier: Topic :: Software Development :: Build Tools
Classifier: License :: OSI Approved :: GNU General Public License v3 (GPLv3)
Classifier: Programming Language :: Python :: 3
Classifier: Programming Language :: Python :: 3.8
Classifier: Programming Language :: Python :: 3.9
Classifier: Programming Language :: Python :: 3 :: Only
Requires-Python: >=3.8, <4
